Metadata-Version: 2.1
Name: portfolio-report-chrislilley
Version: 0.0.1
Summary: Gives you an update on your stock portfolios losses and gains
Author: Chris Lilley
Author-email: christopher.lilley@dcmail.ca
Classifier: Programming Language :: Python :: 3
Classifier: License :: OSI Approved :: MIT License
Classifier: Operating System :: OS Independent
License-File: LICENSE
